{
  "db_name": "SQLite",
  "query": "SELECT\n            audit_log.id as \"id: AuditLogEventId\",\n            time as \"time: _\",\n            json(event) as \"event!: serde_json::Value\",\n            event_level as \"event_level: _\",\n            message,\n            ip as \"ip: String\",\n            user_id as \"user_id: UserId\",\n            username,\n            user_fullname,\n            user_role as \"user_role: Role\"\n        FROM audit_log\n        ORDER BY time DESC\n        ",
  "describe": {
    "columns": [
      {
        "name": "id: AuditLogEventId",
        "ordinal": 0,
        "type_info": "Integer"
      },
      {
        "name": "time: _",
        "ordinal": 1,
        "type_info": "Text"
      },
      {
        "name": "event!: serde_json::Value",
        "ordinal": 2,
        "type_info": "Null"
      },
      {
        "name": "event_level: _",
        "ordinal": 3,
        "type_info": "Text"
      },
      {
        "name": "message",
        "ordinal": 4,
        "type_info": "Text"
      },
      {
        "name": "ip: String",
        "ordinal": 5,
        "type_info": "Text"
      },
      {
        "name": "user_id: UserId",
        "ordinal": 6,
        "type_info": "Integer"
      },
      {
        "name": "username",
        "ordinal": 7,
        "type_info": "Text"
      },
      {
        "name": "user_fullname",
        "ordinal": 8,
        "type_info": "Text"
      },
      {
        "name": "user_role: Role",
        "ordinal": 9,
        "type_info": "Text"
      }
    ],
    "parameters": {
      "Right": 0
    },
    "nullable": [
      false,
      false,
      null,
      false,
      true,
      true,
      true,
      true,
      true,
      true
    ]
  },
  "hash": "0a731bcae1d260caf75faa357b510e6e7d25c0f1ae7f36e0ccdc3ec324bcfc4c"
}
